<?xml version="1.0" encoding="utf-16"?>
<Level width="2">
  <Camera x="0" y="-1" minWidth="25" maxWidth="35" />
  <Score highScore="0" />
  <Birds>
    <Bird type="BirdRed"/>
    <Bird type="BirdRed"/>
  </Birds>
  <Slingshot x="-12.0" y="-2.5" />
  <GameObjects>
    <Pig type="BasicSmall" material="" x="-2.4983" y="-1.1486" rotation="0.439" />
    <Pig type="BasicSmall" material="" x="-4.5014" y="-1.1488" rotation="0.6861" />
    <TNT type="" x="-7.8886" y="-2.0754" rotation="0.0" />
    <Platform type="Platform" material="" x="-3.4882" y="-1.5303" rotation="0.0" scaleX="6.2566" scaleY="0.5" />
    <Platform type="Platform" material="" x="-5.3392" y="-1.0493" rotation="90.0" scaleX="2.0" scaleY="0.5" />
    <Platform type="Platform" material="" x="-1.6482" y="-1.0396" rotation="90.0" scaleX="1.979" scaleY="0.5" />
    <Platform type="Platform" material="" x="-3.5252" y="-0.9003" rotation="90.0" scaleX="1.5158" scaleY="0.5" />
    <Platform type="Platform" material="" x="-7.8782" y="-2.5803" rotation="0.0" scaleX="1.0" scaleY="0.5" />
    <Block type="CircleSmall" material="wood" x="-3.322" y="-3.275" rotation="0" />
    <Block type="SquareTiny" material="stone" x="4.6285" y="-3.39" rotation="0" />
    <Platform type="Platform" material="" x="0.009" y="-3.18" rotation="0" scaleX="1.0" scaleY="1.0" />
    <Block type="SquareSmall" material="ice" x="-5.6957" y="-3.285" rotation="0" />
    <Block type="RectFat" material="stone" x="7.3796" y="-3.285" rotation="0" />
    <ExternalAgent type="Worm" material="" x="-3.4882" y="-1.5303" rotation="0" />
  </GameObjects>
</Level>
