<?xml version="1.0" encoding="utf-16"?>
<Level width="2">
  <Camera x="0" y="-1" minWidth="25" maxWidth="35" />
  <Score highScore="0" />
  <Birds>
    <Bird type="novel_object_247"/>
  </Birds>
  <Slingshot x="-12.0" y="-2.5" />
  <GameObjects>
    <Pig type="BasicSmall" material="" x="-4.2059" y="-1.9178" rotation="0.5998" />
    <Block type="RectBig" material="stone" x="-4.2358" y="-0.0974" rotation="0.0996" />
    <Block type="RectBig" material="stone" x="-4.2658" y="-0.3324" rotation="0.0995" />
    <Platform type="Platform" material="" x="-4.7089" y="-2.2991" rotation="0.0" scaleX="4.7346" scaleY="0.5" />
    <Platform type="Platform" material="" x="-3.3558" y="-1.449" rotation="90.0" scaleX="3.1031" scaleY="0.5" />
    <Platform type="Platform" material="" x="-5.2028" y="-0.6191" rotation="0.0" scaleX="1.0" scaleY="0.5" />
    <Platform type="Platform" material="" x="-5.0558" y="-1.609" rotation="90.0" scaleX="2.5976" scaleY="0.5" />
    <Block type="SquareTiny" material="ice" x="-9.9596" y="-3.39" rotation="0" />
    <Block type="SquareHole" material="wood" x="-4.4826" y="-3.08" rotation="0" />
    <Block type="SquareTiny" material="wood" x="2.4618" y="-3.39" rotation="0" />
    <Block type="RectFat" material="wood" x="5.402" y="-3.285" rotation="0" />
    <Block type="RectMedium" material="ice" x="8.0885" y="-3.39" rotation="0" />
    <ExternalAgent type="Butterfly" material="" x="-10.5126" y="-2.84" rotation="0" />
  </GameObjects>
</Level>
