<?xml version="1.0" encoding="utf-16"?>
<Level width="2">
  <Camera x="0" y="-1" minWidth="25" maxWidth="35" />
  <Score highScore="0" />
  <Birds>
    <Bird type="novel_object_247"/>
  </Birds>
  <Slingshot x="-12.0" y="-2.5" />
  <GameObjects>
    <Pig type="BasicSmall" material="" x="-7.0128" y="-1.8215" rotation="0.5998" />
    <Block type="RectBig" material="stone" x="-7.0426" y="-0.001" rotation="0.0996" />
    <Block type="RectBig" material="stone" x="-7.0726" y="-0.236" rotation="0.0995" />
    <Platform type="Platform" material="" x="-7.5157" y="-2.2028" rotation="0.0" scaleX="4.7346" scaleY="0.5" />
    <Platform type="Platform" material="" x="-6.1626" y="-1.3527" rotation="90.0" scaleX="3.1031" scaleY="0.5" />
    <Platform type="Platform" material="" x="-8.0096" y="-0.5228" rotation="0.0" scaleX="1.0" scaleY="0.5" />
    <Platform type="Platform" material="" x="-7.8626" y="-1.5127" rotation="90.0" scaleX="2.5976" scaleY="0.5" />
    <Platform type="Platform" material="" x="-3.8833" y="-3.18" rotation="0" scaleX="1.0" scaleY="1.0" />
    <Block type="Triangle" material="stone" x="6.8714" y="-3.09" rotation="0" />
    <Block type="SquareTiny" material="stone" x="-8.367" y="-3.39" rotation="0" />
    <Block type="RectBig" material="wood" x="2.2499" y="-3.39" rotation="0" />
    <Block type="RectSmall" material="ice" x="8.5139" y="-3.39" rotation="0" />
    <ExternalAgent type="Butterfly" material="" x="-9.111" y="-2.84" rotation="0" />
  </GameObjects>
</Level>
