<?xml version="1.0" encoding="utf-16"?>
<Level width="2">
  <Camera x="0" y="-1" minWidth="25" maxWidth="35" />
  <Score highScore="0" />
  <Birds>
    <Bird type="novel_object_0"/>
  </Birds>
  <Slingshot x="-12.0" y="-2.5" />
  <GameObjects>
    <Pig type="BasicSmall" material="" x="0.1643" y="1.2117" rotation="0.439" />
    <Pig type="BasicSmall" material="" x="-1.839" y="1.2109" rotation="0.9065" />
    <Platform type="Platform" material="" x="-0.8257" y="0.83" rotation="0.0" scaleX="6.2566" scaleY="0.5" />
    <Platform type="Platform" material="" x="-2.6767" y="1.311" rotation="90.0" scaleX="2.0" scaleY="0.5" />
    <Platform type="Platform" material="" x="1.0143" y="1.3207" rotation="90.0" scaleX="1.979" scaleY="0.5" />
    <Platform type="Platform" material="" x="-0.8627" y="1.46" rotation="90.0" scaleX="1.5158" scaleY="0.5" />
    <Block type="SquareTiny" material="ice" x="8.433" y="-3.39" rotation="0" />
    <Block type="RectSmall" material="ice" x="1.9989" y="-3.39" rotation="0" />
    <Block type="SquareSmall" material="ice" x="-3.3856" y="-3.285" rotation="0" />
  </GameObjects>
</Level>
