<?xml version="1.0" encoding="utf-16"?>
<Level width="2">
  <Camera x="0" y="-1" minWidth="25" maxWidth="35" />
  <Score highScore="0" />
  <Birds>
    <Bird type="novel_object_0"/>
  </Birds>
  <Slingshot x="-12.0" y="-2.5" />
  <GameObjects>
    <Pig type="BasicSmall" material="" x="-1.9746" y="1.5299" rotation="0.439" />
    <Pig type="BasicSmall" material="" x="-3.9779" y="1.5291" rotation="0.9065" />
    <Platform type="Platform" material="" x="-2.9646" y="1.1482" rotation="0.0" scaleX="6.2566" scaleY="0.5" />
    <Platform type="Platform" material="" x="-4.8156" y="1.6292" rotation="90.0" scaleX="2.0" scaleY="0.5" />
    <Platform type="Platform" material="" x="-1.1246" y="1.6389" rotation="90.0" scaleX="1.979" scaleY="0.5" />
    <Platform type="Platform" material="" x="-3.0016" y="1.7782" rotation="90.0" scaleX="1.5158" scaleY="0.5" />
    <Block type="RectSmall" material="wood" x="-4.6572" y="-3.39" rotation="0" />
    <Block type="RectBig" material="wood" x="-1.9315" y="-3.39" rotation="0" />
  </GameObjects>
</Level>
