<?xml version="1.0" encoding="utf-16"?>
<Level width="2">
  <Camera x="0" y="-1" minWidth="25" maxWidth="35" />
  <Score highScore="0" />
  <Birds>
    <Bird type="BirdRed"/>
    <Bird type="BirdRed"/>
  </Birds>
  <Slingshot x="-12.0" y="-2.5" />
  <GameObjects>
    <Pig type="BasicSmall" material="" x="-3.4422" y="1.993" rotation="0.439" />
    <Pig type="BasicSmall" material="" x="-5.4453" y="1.9928" rotation="0.6875" />
    <Platform type="Platform" material="" x="-4.4321" y="1.6113" rotation="0.0" scaleX="6.2566" scaleY="0.5" />
    <Platform type="Platform" material="" x="-6.2831" y="2.0923" rotation="90.0" scaleX="2.0" scaleY="0.5" />
    <Platform type="Platform" material="" x="-2.5921" y="2.102" rotation="90.0" scaleX="1.979" scaleY="0.5" />
    <Platform type="Platform" material="" x="-4.4691" y="2.2413" rotation="90.0" scaleX="1.5158" scaleY="0.5" />
    <Block type="RectTiny" material="wood" x="0.432" y="-3.39" rotation="0" />
    <Platform type="Platform" material="" x="-9.2386" y="-3.18" rotation="0" scaleX="1.0" scaleY="1.0" />
    <Block type="TriangleHole" material="stone" x="2.4624" y="-3.09" rotation="0" />
  </GameObjects>
</Level>
