<?xml version="1.0" encoding="utf-16"?>
<Level width="2">
  <Camera x="0" y="-1" minWidth="25" maxWidth="35" />
  <Score highScore="0" />
  <Birds>
    <Bird type="BirdRed"/>
  </Birds>
  <Slingshot x="-12.0" y="-2.5" />
  <GameObjects>
    <Pig type="BasicSmall" material="" x="-4.3933" y="-0.9302" rotation="0.3056" />
    <Platform type="Platform" material="" x="-5.3439" y="-1.3134" rotation="0.0" scaleX="4.7346" scaleY="0.5" />
    <Platform type="Platform" material="" x="-3.9908" y="-0.4633" rotation="90.0" scaleX="3.1031" scaleY="0.5" />
    <Platform type="Platform" material="" x="-5.8378" y="0.3666" rotation="0.0" scaleX="1.0" scaleY="0.5" />
    <Platform type="Platform" material="" x="-5.6908" y="-0.6233" rotation="90.0" scaleX="2.5976" scaleY="0.5" />
    <Block type="Circle" material="ice" x="6.5336" y="-3.1" rotation="0" />
    <Block type="RectBig" material="ice" x="-3.01" y="-3.39" rotation="0" />
    <ExternalAgent type="Magician" material="" x="1.6341" y="-2.8293" rotation="0" />
  </GameObjects>
</Level>
