<?xml version="1.0" encoding="utf-16"?>
<Level width="2">
  <Camera x="0" y="-1" minWidth="25" maxWidth="35" />
  <Score highScore="0" />
  <Birds>
    <Bird type="BirdRed"/>
  </Birds>
  <Slingshot x="-12.0" y="-2.5" />
  <GameObjects>
    <Pig type="BasicSmall" material="" x="8.07" y="-2.0614" rotation="0.4278" />
    <Platform type="Platform" material="" x="-2.0188" y="-2.4431" rotation="0.0" scaleX="4.7346" scaleY="0.5" />
    <Platform type="Platform" material="" x="-0.6657" y="-1.593" rotation="90.0" scaleX="3.1031" scaleY="0.5" />
    <Platform type="Platform" material="" x="-2.5127" y="-0.7631" rotation="0.0" scaleX="1.0" scaleY="0.5" />
    <Platform type="Platform" material="" x="-2.3577" y="-1.5231" rotation="0.0" scaleX="0.536" scaleY="2.886" />
    <Platform type="Platform" material="" x="7.1543" y="-2.4431" rotation="0.0" scaleX="4.7346" scaleY="0.5" />
    <Platform type="Platform" material="" x="8.5074" y="-1.593" rotation="90.0" scaleX="3.1031" scaleY="0.5" />
    <Platform type="Platform" material="" x="6.6604" y="-0.7631" rotation="0.0" scaleX="1.0" scaleY="0.5" />
    <Platform type="Platform" material="" x="6.8154" y="-1.5231" rotation="0.0" scaleX="0.536" scaleY="2.886" />
    <ExternalAgent type="novel_object_224" material="" x="-1.5257" y="-0.3831" rotation="90.0" />
    <ExternalAgent type="novel_object_224" material="" x="7.6543" y="-0.3831" rotation="90.0" />
    <Block type="Circle" material="wood" x="4.4517" y="-3.1" rotation="0" />
    <Block type="RectMedium" material="ice" x="-5.4886" y="-3.39" rotation="0" />
    <Block type="CircleSmall" material="ice" x="1.6972" y="-3.275" rotation="0" />
    <Block type="SquareTiny" material="ice" x="-8.7917" y="-3.39" rotation="0" />
    <Platform type="Platform" material="" x="-7.5898" y="-3.18" rotation="0" scaleX="1.0" scaleY="1.0" />
    <ExternalAgent type="Butterfly" material="" x="-9.7389" y="-2.84" rotation="0" />
  </GameObjects>
</Level>
