<?xml version="1.0" encoding="utf-16"?>
<Level width="2">
  <Camera x="0" y="-1" minWidth="25" maxWidth="35" />
  <Score highScore="0" />
  <Birds>
    <Bird type="BirdRed"/>
  </Birds>
  <Slingshot x="-12.0" y="-2.5" />
  <GameObjects>
    <Pig type="BasicSmall" material="" x="7.3861" y="-1.9326" rotation="0.4278" />
    <Platform type="Platform" material="" x="-2.7028" y="-2.3143" rotation="0.0" scaleX="4.7346" scaleY="0.5" />
    <Platform type="Platform" material="" x="-1.3497" y="-1.4642" rotation="90.0" scaleX="3.1031" scaleY="0.5" />
    <Platform type="Platform" material="" x="-3.1967" y="-0.6343" rotation="0.0" scaleX="1.0" scaleY="0.5" />
    <Platform type="Platform" material="" x="-3.0417" y="-1.3943" rotation="0.0" scaleX="0.536" scaleY="2.886" />
    <Platform type="Platform" material="" x="6.4703" y="-2.3143" rotation="0.0" scaleX="4.7346" scaleY="0.5" />
    <Platform type="Platform" material="" x="7.8234" y="-1.4642" rotation="90.0" scaleX="3.1031" scaleY="0.5" />
    <Platform type="Platform" material="" x="5.9764" y="-0.6343" rotation="0.0" scaleX="1.0" scaleY="0.5" />
    <Platform type="Platform" material="" x="6.1314" y="-1.3943" rotation="0.0" scaleX="0.536" scaleY="2.886" />
    <ExternalAgent type="novel_object_224" material="" x="-2.2097" y="-0.2543" rotation="90.0" />
    <ExternalAgent type="novel_object_224" material="" x="6.9703" y="-0.2543" rotation="90.0" />
    <Platform type="Platform" material="" x="-0.7832" y="-3.18" rotation="0" scaleX="1.0" scaleY="1.0" />
    <Block type="RectSmall" material="ice" x="4.4919" y="-3.39" rotation="0" />
    <Block type="CircleSmall" material="ice" x="7.6876" y="-3.275" rotation="0" />
    <Block type="SquareTiny" material="stone" x="2.5904" y="-3.39" rotation="0" />
    <Block type="SquareSmall" material="wood" x="-7.6771" y="-3.285" rotation="0" />
    <ExternalAgent type="Butterfly" material="" x="8.6305" y="-2.84" rotation="0" />
  </GameObjects>
</Level>
