<?xml version="1.0" encoding="utf-16"?>
<Level width="2">
  <Camera x="0" y="-1" minWidth="25" maxWidth="35" />
  <Score highScore="0" />
  <Birds>
    <Bird type="BirdRed"/>
  </Birds>
  <Slingshot x="-12.0" y="-2.5" />
  <GameObjects>
    <Pig type="BasicSmall" material="" x="-3.2382" y="1.2871" rotation="0.5998" />
    <TNT type="" x="-4.658" y="1.4108" rotation="0.0" />
    <Block type="RectBig" material="stone" x="-3.2481" y="3.1075" rotation="0.1028" />
    <Block type="RectBig" material="stone" x="-3.2452" y="2.8726" rotation="0.1026" />
    <Platform type="Platform" material="" x="-3.7411" y="0.9058" rotation="0.0" scaleX="4.7346" scaleY="0.5" />
    <Platform type="Platform" material="" x="-2.388" y="1.7559" rotation="90.0" scaleX="3.1031" scaleY="0.5" />
    <Platform type="Platform" material="" x="-4.235" y="2.5858" rotation="0.0" scaleX="1.0" scaleY="0.5" />
    <Platform type="Platform" material="" x="-4.088" y="1.5959" rotation="90.0" scaleX="2.5976" scaleY="0.5" />
    <Platform type="Platform" material="" x="-9.1626" y="-3.18" rotation="0" scaleX="1.0" scaleY="1.0" />
    <Block type="RectBig" material="ice" x="-0.458" y="-3.39" rotation="0" />
    <Block type="SquareSmall" material="ice" x="-3.6197" y="-3.285" rotation="0" />
    <ExternalAgent type="Magician" material="" x="3.4945" y="-2.8293" rotation="0" />
  </GameObjects>
</Level>
