<?xml version="1.0" encoding="utf-16"?>
<Level width="2">
  <Camera x="0" y="-1" minWidth="25" maxWidth="35" />
  <Score highScore="0" />
  <Birds>
    <Bird type="BirdRed"/>
  </Birds>
  <Slingshot x="-12.0" y="-2.5" />
  <GameObjects>
    <Pig type="BasicSmall" material="" x="2.9514" y="0.9241" rotation="0.4278" />
    <Platform type="Platform" material="" x="-7.1374" y="0.5424" rotation="0.0" scaleX="4.7346" scaleY="0.5" />
    <Platform type="Platform" material="" x="-5.7843" y="1.3925" rotation="90.0" scaleX="3.1031" scaleY="0.5" />
    <Platform type="Platform" material="" x="-7.6313" y="2.2224" rotation="0.0" scaleX="1.0" scaleY="0.5" />
    <Platform type="Platform" material="" x="-7.4763" y="1.4624" rotation="0.0" scaleX="0.536" scaleY="2.886" />
    <Platform type="Platform" material="" x="2.0357" y="0.5424" rotation="0.0" scaleX="4.7346" scaleY="0.5" />
    <Platform type="Platform" material="" x="3.3888" y="1.3925" rotation="90.0" scaleX="3.1031" scaleY="0.5" />
    <Platform type="Platform" material="" x="1.5418" y="2.2224" rotation="0.0" scaleX="1.0" scaleY="0.5" />
    <Platform type="Platform" material="" x="1.6968" y="1.4624" rotation="0.0" scaleX="0.536" scaleY="2.886" />
    <ExternalAgent type="novel_object_224" material="" x="-6.6443" y="2.6024" rotation="90.0" />
    <ExternalAgent type="novel_object_224" material="" x="2.5357" y="2.6024" rotation="90.0" />
    <Block type="RectSmall" material="wood" x="-5.649" y="-3.39" rotation="0" />
    <Block type="SquareTiny" material="ice" x="-7.247" y="-3.39" rotation="0" />
    <Block type="SquareHole" material="stone" x="3.1893" y="-3.08" rotation="0" />
    <Block type="SquareHole" material="wood" x="0.9361" y="-3.08" rotation="0" />
  </GameObjects>
</Level>
