<?xml version="1.0" encoding="utf-16"?>
<Level width="2">
  <Camera x="0" y="-1" minWidth="25" maxWidth="35" />
  <Score highScore="0" />
  <Birds>
    <Bird type="BirdRed"/>
  </Birds>
  <Slingshot x="-12.0" y="-2.5" />
  <GameObjects>
    <Pig type="BasicSmall" material="" x="5.6011" y="-1.5911" rotation="0.4278" />
    <Platform type="Platform" material="" x="-4.4878" y="-1.9728" rotation="0.0" scaleX="4.7346" scaleY="0.5" />
    <Platform type="Platform" material="" x="-3.1347" y="-1.1227" rotation="90.0" scaleX="3.1031" scaleY="0.5" />
    <Platform type="Platform" material="" x="-4.9817" y="-0.2928" rotation="0.0" scaleX="1.0" scaleY="0.5" />
    <Platform type="Platform" material="" x="-4.8267" y="-1.0528" rotation="0.0" scaleX="0.536" scaleY="2.886" />
    <Platform type="Platform" material="" x="4.6853" y="-1.9728" rotation="0.0" scaleX="4.7346" scaleY="0.5" />
    <Platform type="Platform" material="" x="6.0384" y="-1.1227" rotation="90.0" scaleX="3.1031" scaleY="0.5" />
    <Platform type="Platform" material="" x="4.1914" y="-0.2928" rotation="0.0" scaleX="1.0" scaleY="0.5" />
    <Platform type="Platform" material="" x="4.3464" y="-1.0528" rotation="0.0" scaleX="0.536" scaleY="2.886" />
    <ExternalAgent type="novel_object_224" material="" x="-3.9947" y="0.0872" rotation="90.0" />
    <ExternalAgent type="novel_object_224" material="" x="5.1853" y="0.0872" rotation="90.0" />
    <Block type="Triangle" material="wood" x="2.9435" y="-3.09" rotation="0" />
    <Block type="RectBig" material="wood" x="-6.7188" y="-3.39" rotation="0" />
    <Block type="CircleSmall" material="ice" x="7.6101" y="-3.275" rotation="0" />
    <Block type="RectMedium" material="stone" x="-0.8801" y="-3.39" rotation="0" />
    <Block type="RectSmall" material="stone" x="5.3184" y="-3.39" rotation="0" />
  </GameObjects>
</Level>
