<?xml version="1.0" encoding="utf-16"?>
<Level width="2">
  <Camera x="0" y="-1" minWidth="25" maxWidth="35" />
  <Score highScore="0" />
  <Birds>
    <Bird type="BirdYellow"/>
  </Birds>
  <Slingshot x="-12.0" y="-2.5" />
  <GameObjects>
    <Pig type="BasicSmall" material="" x="-1.4378" y="-0.3069" rotation="0.5998" />
    <Block type="RectBig" material="wood" x="-1.4728" y="1.0747" rotation="0.1008" />
    <Block type="RectBig" material="stone" x="-2.7829" y="0.3138" rotation="90.5252" />
    <Platform type="Platform" material="" x="-1.9415" y="-0.8921" rotation="0.0" scaleX="4.7346" scaleY="0.5" />
    <Platform type="Platform" material="" x="-0.5884" y="-0.042" rotation="90.0" scaleX="3.1031" scaleY="0.5" />
    <Platform type="Platform" material="" x="-2.3878" y="0.7879" rotation="0.0" scaleX="0.8531" scaleY="0.5" />
    <Platform type="Platform" material="" x="-1.5358" y="-0.7801" rotation="0.0" scaleX="3.4476" scaleY="0.7871" />
    <Platform type="Platform" material="" x="-3.1912" y="-0.8021" rotation="0.0" scaleX="0.8429" scaleY="0.7871" />
    <Block type="SquareHole" material="ice" x="-1.9374" y="-3.08" rotation="0" />
    <Block type="CircleSmall" material="wood" x="6.6714" y="-3.275" rotation="0" />
    <Block type="SquareSmall" material="ice" x="-6.6235" y="-3.285" rotation="0" />
    <Block type="SquareTiny" material="ice" x="-8.3859" y="-3.39" rotation="0" />
  </GameObjects>
</Level>
