<?xml version="1.0" encoding="utf-16"?>
<Level width="2">
  <Camera x="0" y="-1" minWidth="25" maxWidth="35" />
  <Score highScore="0" />
  <Birds>
    <Bird type="BirdRed"/>
  </Birds>
  <Slingshot x="-12.0" y="-2.5" />
  <GameObjects>
    <Pig type="BasicSmall" material="" x="-1.7432" y="-0.9842" rotation="0.5998" />
    <Platform type="Platform" material="" x="-2.2462" y="-1.3655" rotation="0.0" scaleX="4.7346" scaleY="0.5" />
    <Platform type="Platform" material="" x="-0.893" y="-0.5154" rotation="90.0" scaleX="3.1031" scaleY="0.5" />
    <Platform type="Platform" material="" x="-2.7401" y="0.3145" rotation="0.0" scaleX="1.0" scaleY="0.5" />
    <Platform type="Platform" material="" x="-2.593" y="-0.6754" rotation="90.0" scaleX="2.5976" scaleY="0.5" />
    <Block type="TriangleHole" material="stone" x="4.8727" y="-3.09" rotation="0" />
    <Block type="RectFat" material="wood" x="-7.3034" y="-3.285" rotation="0" />
    <Block type="RectTiny" material="stone" x="2.635" y="-3.39" rotation="0" />
    <Block type="RectMedium" material="stone" x="-5.5369" y="-3.39" rotation="0" />
    <ExternalAgent type="Wizard" material="" x="0.5784" y="3.057" rotation="0" />
  </GameObjects>
</Level>
