<?xml version="1.0" encoding="utf-16"?>
<Level width="2">
  <Camera x="0" y="-1" minWidth="25" maxWidth="35" />
  <Score highScore="0" />
  <Birds>
    <Bird type="BirdRed"/>
  </Birds>
  <Slingshot x="-12.0" y="-2.5" />
  <GameObjects>
    <Pig type="BasicSmall" material="" x="3.865" y="-0.8933" rotation="0.5998" />
    <Platform type="Platform" material="" x="3.3621" y="-1.2747" rotation="0.0" scaleX="4.7346" scaleY="0.5" />
    <Block type="SquareTiny" material="ice" x="-1.3953" y="-3.39" rotation="0" />
    <Platform type="Platform" material="" x="-3.2428" y="-3.18" rotation="0" scaleX="1.0" scaleY="1.0" />
    <Block type="RectSmall" material="ice" x="8.3892" y="-3.39" rotation="0" />
    <Block type="SquareSmall" material="wood" x="-7.7876" y="-3.285" rotation="0" />
    <Block type="RectSmall" material="stone" x="6.0279" y="-3.39" rotation="0" />
    <ExternalAgent type="Butterfly" material="" x="-9.6688" y="-2.84" rotation="0" />
  </GameObjects>
</Level>
