<?xml version="1.0" encoding="utf-16"?>
<Level width="2">
  <Camera x="0" y="-1" minWidth="25" maxWidth="35" />
  <Score highScore="0" />
  <Birds>
    <Bird type="novel_object_247"/>
  </Birds>
  <Slingshot x="-12.0" y="-2.5" />
  <GameObjects>
    <Pig type="BasicSmall" material="" x="-1.4345" y="-2.7035" rotation="0.5998" />
    <Block type="RectBig" material="stone" x="-1.4643" y="-0.883" rotation="0.0996" />
    <Block type="RectBig" material="stone" x="-1.4943" y="-1.1181" rotation="0.0995" />
    <Platform type="Platform" material="" x="-1.9374" y="-3.0848" rotation="0.0" scaleX="4.7346" scaleY="0.5" />
    <Platform type="Platform" material="" x="-0.5843" y="-2.2347" rotation="90.0" scaleX="3.1031" scaleY="0.5" />
    <Platform type="Platform" material="" x="-2.4313" y="-1.4048" rotation="0.0" scaleX="1.0" scaleY="0.5" />
    <Platform type="Platform" material="" x="-2.2843" y="-2.3947" rotation="90.0" scaleX="2.5976" scaleY="0.5" />
    <Block type="TriangleHole" material="wood" x="6.4785" y="-3.09" rotation="0" />
    <Block type="RectSmall" material="stone" x="-6.5849" y="-3.39" rotation="0" />
    <ExternalAgent type="Magician" material="" x="2.2867" y="-2.8293" rotation="0" />
  </GameObjects>
</Level>
