<?xml version="1.0" encoding="utf-16"?>
<Level width="2">
  <Camera x="0" y="-1" minWidth="25" maxWidth="35" />
  <Score highScore="0" />
  <Birds>
    <Bird type="BirdRed"/>
  </Birds>
  <Slingshot x="-12.0" y="-2.5" />
  <GameObjects>
    <Pig type="BasicSmall" material="" x="0.0668" y="-3.2746" rotation="0.5997" />
    <Platform type="Platform" material="" x="-0.4361" y="-3.656" rotation="0.0" scaleX="4.7346" scaleY="0.5" />
    <Platform type="Platform" material="" x="0.917" y="-2.8059" rotation="90.0" scaleX="3.1031" scaleY="0.5" />
    <Platform type="Platform" material="" x="-0.93" y="-1.976" rotation="0.0" scaleX="1.0" scaleY="0.5" />
    <Platform type="Platform" material="" x="-0.783" y="-2.9659" rotation="90.0" scaleX="2.5976" scaleY="0.5" />
    <Block type="SquareTiny" material="wood" x="-6.199" y="-3.39" rotation="0" />
    <Block type="SquareHole" material="stone" x="8.9253" y="-3.08" rotation="0" />
    <Block type="TriangleHole" material="wood" x="6.1744" y="-3.09" rotation="0" />
    <Block type="Circle" material="ice" x="-8.0769" y="-3.1" rotation="0" />
  </GameObjects>
</Level>
