<?xml version="1.0" encoding="utf-16"?>
<Level width="2">
  <Camera x="0" y="-1" minWidth="25" maxWidth="35" />
  <Score highScore="0" />
  <Birds>
    <Bird type="BirdRed"/>
    <Bird type="BirdRed"/>
  </Birds>
  <Slingshot x="-12.0" y="-2.5" />
  <GameObjects>
    <Pig type="BasicSmall" material="" x="-2.6406" y="0.718" rotation="0.439" />
    <Pig type="BasicSmall" material="" x="-4.6437" y="0.7178" rotation="0.6861" />
    <TNT type="" x="-8.0309" y="-0.2088" rotation="0.0" />
    <Platform type="Platform" material="" x="-3.6305" y="0.3363" rotation="0.0" scaleX="6.2566" scaleY="0.5" />
    <Platform type="Platform" material="" x="-5.4815" y="0.8173" rotation="90.0" scaleX="2.0" scaleY="0.5" />
    <Platform type="Platform" material="" x="-1.7905" y="0.827" rotation="90.0" scaleX="1.979" scaleY="0.5" />
    <Platform type="Platform" material="" x="-3.6675" y="0.9663" rotation="90.0" scaleX="1.5158" scaleY="0.5" />
    <Platform type="Platform" material="" x="-8.0205" y="-0.7137" rotation="0.0" scaleX="1.0" scaleY="0.5" />
    <Block type="SquareSmall" material="stone" x="7.939" y="-3.285" rotation="0" />
    <Block type="RectSmall" material="stone" x="-1.433" y="-3.39" rotation="0" />
    <Block type="RectBig" material="ice" x="-4.4399" y="-3.39" rotation="0" />
    <Block type="RectTiny" material="stone" x="6.3358" y="-3.39" rotation="0" />
    <Block type="RectFat" material="wood" x="4.3107" y="-3.285" rotation="0" />
    <ExternalAgent type="Wizard" material="" x="1.3267" y="1.4391" rotation="0" />
  </GameObjects>
</Level>
