<?xml version="1.0" encoding="utf-16"?>
<Level width="2">
  <Camera x="0" y="-1" minWidth="25" maxWidth="35" />
  <Score highScore="0" />
  <Birds>
    <Bird type="BirdRed"/>
  </Birds>
  <Slingshot x="-12.0" y="-2.5" />
  <GameObjects>
    <Pig type="BasicSmall" material="" x="-0.0214" y="-1.3641" rotation="0.5998" />
    <Platform type="Platform" material="" x="-0.5244" y="-1.7455" rotation="0.0" scaleX="4.7346" scaleY="0.5" />
    <Platform type="Platform" material="" x="0.8287" y="-0.8954" rotation="90.0" scaleX="3.1031" scaleY="0.5" />
    <Platform type="Platform" material="" x="-0.1873" y="-0.0655" rotation="0.0" scaleX="3.5953" scaleY="0.5" />
    <Block type="RectTiny" material="ice" x="1.087" y="-3.39" rotation="0" />
    <Block type="SquareTiny" material="wood" x="-1.462" y="-3.39" rotation="0" />
    <ExternalAgent type="Butterfly" material="" x="-7.2249" y="-2.84" rotation="0" />
  </GameObjects>
</Level>
