<?xml version="1.0" encoding="utf-16"?>
<Level width="2">
  <Camera x="0" y="-1" minWidth="25" maxWidth="35" />
  <Score highScore="0" />
  <Birds>
    <Bird type="novel_object_247"/>
  </Birds>
  <Slingshot x="-12.0" y="-2.5" />
  <GameObjects>
    <Pig type="BasicSmall" material="" x="-5.0313" y="-1.4999" rotation="0.5998" />
    <Block type="RectBig" material="stone" x="-5.0611" y="0.3206" rotation="0.0996" />
    <Block type="RectBig" material="stone" x="-5.0911" y="0.0856" rotation="0.0995" />
    <Platform type="Platform" material="" x="-5.5342" y="-1.8812" rotation="0.0" scaleX="4.7346" scaleY="0.5" />
    <Platform type="Platform" material="" x="-4.1811" y="-1.0311" rotation="90.0" scaleX="3.1031" scaleY="0.5" />
    <Platform type="Platform" material="" x="-6.0281" y="-0.2012" rotation="0.0" scaleX="1.0" scaleY="0.5" />
    <Platform type="Platform" material="" x="-5.8811" y="-1.1911" rotation="90.0" scaleX="2.5976" scaleY="0.5" />
    <Block type="SquareHole" material="stone" x="-2.8182" y="-3.08" rotation="0" />
    <ExternalAgent type="Worm" material="" x="-5.5342" y="-1.8812" rotation="0" />
  </GameObjects>
</Level>
