<?xml version="1.0" encoding="utf-16"?>
<Level width="2">
  <Camera x="0" y="-1" minWidth="25" maxWidth="35" />
  <Score highScore="0" />
  <Birds>
    <Bird type="BirdRed"/>
  </Birds>
  <Slingshot x="-12.0" y="-2.5" />
  <GameObjects>
    <Pig type="BasicSmall" material="" x="-2.8199" y="1.1356" rotation="0.5997" />
    <Platform type="Platform" material="" x="-3.3229" y="0.7543" rotation="0.0" scaleX="4.7346" scaleY="0.5" />
    <Platform type="Platform" material="" x="-1.9698" y="1.6044" rotation="90.0" scaleX="3.1031" scaleY="0.5" />
    <Platform type="Platform" material="" x="-3.8168" y="2.4343" rotation="0.0" scaleX="1.0" scaleY="0.5" />
    <Platform type="Platform" material="" x="-3.6698" y="1.4444" rotation="90.0" scaleX="2.5976" scaleY="0.5" />
    <ExternalAgent type="novel_object_234" material="" x="-4.7399" y="5.5556" rotation="0.0" />
    <Block type="TriangleHole" material="ice" x="7.6481" y="-3.09" rotation="0" />
    <Block type="CircleSmall" material="ice" x="-5.1601" y="-3.275" rotation="0" />
  </GameObjects>
</Level>
