<?xml version="1.0" encoding="utf-16"?>
<Level width="2">
  <Camera x="0" y="-1" minWidth="25" maxWidth="35" />
  <Score highScore="0" />
  <Birds>
    <Bird type="BirdRed"/>
  </Birds>
  <Slingshot x="-12.0" y="-2.5" />
  <GameObjects>
    <Pig type="BasicSmall" material="" x="-4.9958" y="-2.4952" rotation="0.5998" />
    <TNT type="" x="-6.4157" y="-2.3716" rotation="0.0" />
    <Block type="RectBig" material="stone" x="-5.0058" y="-0.6749" rotation="0.1028" />
    <Block type="RectBig" material="stone" x="-5.0029" y="-0.9098" rotation="0.1026" />
    <Platform type="Platform" material="" x="-5.4988" y="-2.8766" rotation="0.0" scaleX="4.7346" scaleY="0.5" />
    <Platform type="Platform" material="" x="-4.1457" y="-2.0265" rotation="90.0" scaleX="3.1031" scaleY="0.5" />
    <Platform type="Platform" material="" x="-5.9927" y="-1.1966" rotation="0.0" scaleX="1.0" scaleY="0.5" />
    <Platform type="Platform" material="" x="-5.8457" y="-2.1865" rotation="90.0" scaleX="2.5976" scaleY="0.5" />
    <Block type="SquareSmall" material="stone" x="3.8228" y="-3.285" rotation="0" />
    <Block type="CircleSmall" material="ice" x="-0.1721" y="-3.275" rotation="0" />
    <Block type="CircleSmall" material="stone" x="-9.4277" y="-3.275" rotation="0" />
    <Block type="RectTiny" material="wood" x="5.9798" y="-3.39" rotation="0" />
    <Block type="RectMedium" material="ice" x="9.1025" y="-3.39" rotation="0" />
    <ExternalAgent type="Wizard" material="" x="-2.5993" y="0.3707" rotation="0" />
  </GameObjects>
</Level>
