<?xml version="1.0" encoding="utf-16"?>
<Level width="2">
  <Camera x="0" y="-1" minWidth="25" maxWidth="35" />
  <Score highScore="0" />
  <Birds>
    <Bird type="BirdRed"/>
    <Bird type="BirdRed"/>
  </Birds>
  <Slingshot x="-12.0" y="-2.5" />
  <GameObjects>
    <Pig type="BasicSmall" material="" x="-2.6054" y="-0.2956" rotation="0.439" />
    <Pig type="BasicSmall" material="" x="-4.6085" y="-0.2957" rotation="0.6861" />
    <TNT type="" x="-7.9957" y="-1.2224" rotation="0.0" />
    <Platform type="Platform" material="" x="-3.5953" y="-0.6773" rotation="0.0" scaleX="6.2566" scaleY="0.5" />
    <Platform type="Platform" material="" x="-5.4463" y="-0.1963" rotation="90.0" scaleX="2.0" scaleY="0.5" />
    <Platform type="Platform" material="" x="-1.7553" y="-0.1866" rotation="90.0" scaleX="1.979" scaleY="0.5" />
    <Platform type="Platform" material="" x="-3.6323" y="-0.0473" rotation="90.0" scaleX="1.5158" scaleY="0.5" />
    <Platform type="Platform" material="" x="-7.9853" y="-1.7273" rotation="0.0" scaleX="1.0" scaleY="0.5" />
    <Block type="RectMedium" material="wood" x="7.9292" y="-3.39" rotation="0" />
    <Block type="TriangleHole" material="stone" x="0.3422" y="-3.09" rotation="0" />
    <Block type="RectBig" material="ice" x="-7.9921" y="-3.39" rotation="0" />
    <Block type="TriangleHole" material="ice" x="-4.1813" y="-3.09" rotation="0" />
    <ExternalAgent type="Butterfly" material="" x="-9.8088" y="-2.84" rotation="0" />
  </GameObjects>
</Level>
