<?xml version="1.0" encoding="utf-16"?>
<Level width="2">
  <Camera x="0" y="-1" minWidth="25" maxWidth="35" />
  <Score highScore="0" />
  <Birds>
    <Bird type="BirdRed"/>
    <Bird type="BirdRed"/>
  </Birds>
  <Slingshot x="-12.0" y="-2.5" />
  <GameObjects>
    <Pig type="BasicSmall" material="" x="0.0924" y="-1.7232" rotation="0.439" />
    <Pig type="BasicSmall" material="" x="-1.9107" y="-1.7234" rotation="0.6861" />
    <TNT type="" x="-5.2979" y="-2.65" rotation="0.0" />
    <Platform type="Platform" material="" x="-0.8975" y="-2.1049" rotation="0.0" scaleX="6.2566" scaleY="0.5" />
    <Platform type="Platform" material="" x="-2.7485" y="-1.6239" rotation="90.0" scaleX="2.0" scaleY="0.5" />
    <Platform type="Platform" material="" x="0.9425" y="-1.6142" rotation="90.0" scaleX="1.979" scaleY="0.5" />
    <Platform type="Platform" material="" x="-0.9345" y="-1.4749" rotation="90.0" scaleX="1.5158" scaleY="0.5" />
    <Platform type="Platform" material="" x="-5.2875" y="-3.1549" rotation="0.0" scaleX="1.0" scaleY="0.5" />
    <Block type="RectFat" material="ice" x="-2.6801" y="-3.285" rotation="0" />
    <Block type="SquareHole" material="ice" x="-7.2491" y="-3.08" rotation="0" />
    <Block type="RectSmall" material="stone" x="8.2156" y="-3.39" rotation="0" />
    <ExternalAgent type="Magician" material="" x="2.2297" y="-2.8293" rotation="0" />
  </GameObjects>
</Level>
