<?xml version="1.0" encoding="utf-16"?>
<Level width="2">
  <Camera x="0" y="-1" minWidth="25" maxWidth="35" />
  <Score highScore="0" />
  <Birds>
    <Bird type="novel_object_247"/>
  </Birds>
  <Slingshot x="-12.0" y="-2.5" />
  <GameObjects>
    <Pig type="BasicSmall" material="" x="-0.3921" y="0.6577" rotation="0.5998" />
    <Block type="RectBig" material="stone" x="-0.4219" y="2.4781" rotation="0.0996" />
    <Block type="RectBig" material="stone" x="-0.4519" y="2.2431" rotation="0.0995" />
    <Platform type="Platform" material="" x="-0.895" y="0.2763" rotation="0.0" scaleX="4.7346" scaleY="0.5" />
    <Platform type="Platform" material="" x="0.4581" y="1.1264" rotation="90.0" scaleX="3.1031" scaleY="0.5" />
    <Platform type="Platform" material="" x="-1.3889" y="1.9563" rotation="0.0" scaleX="1.0" scaleY="0.5" />
    <Platform type="Platform" material="" x="-1.2419" y="0.9664" rotation="90.0" scaleX="2.5976" scaleY="0.5" />
    <Block type="RectTiny" material="ice" x="-4.6585" y="-3.39" rotation="0" />
    <Block type="SquareTiny" material="stone" x="6.4928" y="-3.39" rotation="0" />
    <Block type="RectFat" material="stone" x="0.7735" y="-3.285" rotation="0" />
    <ExternalAgent type="Wizard" material="" x="-5.0477" y="2.4124" rotation="0" />
  </GameObjects>
</Level>
