<?xml version="1.0" encoding="utf-16"?>
<Level width="2">
  <Camera x="0" y="-1" minWidth="25" maxWidth="35" />
  <Score highScore="0" />
  <Birds>
    <Bird type="BirdRed"/>
  </Birds>
  <Slingshot x="-12.0" y="-2.5" />
  <GameObjects>
    <Pig type="BasicSmall" material="" x="-5.1105" y="1.8725" rotation="0.5998" />
    <Platform type="Platform" material="" x="-5.6135" y="1.4912" rotation="0.0" scaleX="4.7346" scaleY="0.5" />
    <Platform type="Platform" material="" x="-4.2604" y="2.3413" rotation="90.0" scaleX="3.1031" scaleY="0.5" />
    <Platform type="Platform" material="" x="-6.1074" y="3.1712" rotation="0.0" scaleX="1.0" scaleY="0.5" />
    <Platform type="Platform" material="" x="-5.9604" y="2.1813" rotation="90.0" scaleX="2.5976" scaleY="0.5" />
    <Block type="SquareTiny" material="ice" x="-8.1791" y="-3.39" rotation="0" />
    <Block type="RectFat" material="stone" x="-6.6513" y="-3.285" rotation="0" />
    <Block type="RectTiny" material="stone" x="3.2593" y="-3.39" rotation="0" />
    <Block type="SquareHole" material="stone" x="8.2592" y="-3.08" rotation="0" />
    <Block type="SquareHole" material="stone" x="-3.3257" y="-3.08" rotation="0" />
    <ExternalAgent type="Wizard" material="" x="1.5615" y="-0.9586" rotation="0" />
  </GameObjects>
</Level>
