<?xml version="1.0" encoding="utf-16"?>
<Level width="2">
  <Camera x="0" y="-1" minWidth="25" maxWidth="35" />
  <Score highScore="0" />
  <Birds>
    <Bird type="BirdRed"/>
  </Birds>
  <Slingshot x="-12.0" y="-2.5" />
  <GameObjects>
    <Pig type="BasicSmall" material="" x="-7.2505" y="-1.154" rotation="0.3056" />
    <Platform type="Platform" material="" x="-8.2011" y="-1.5372" rotation="0.0" scaleX="4.7346" scaleY="0.5" />
    <Platform type="Platform" material="" x="-6.848" y="-0.6871" rotation="90.0" scaleX="3.1031" scaleY="0.5" />
    <Platform type="Platform" material="" x="-8.695" y="0.1428" rotation="0.0" scaleX="1.0" scaleY="0.5" />
    <Platform type="Platform" material="" x="-8.548" y="-0.8471" rotation="90.0" scaleX="2.5976" scaleY="0.5" />
    <Block type="RectMedium" material="stone" x="-5.6985" y="-3.39" rotation="0" />
    <Block type="Circle" material="wood" x="3.4966" y="-3.1" rotation="0" />
    <Block type="RectSmall" material="wood" x="7.3782" y="-3.39" rotation="0" />
    <Block type="TriangleHole" material="ice" x="-0.8317" y="-3.09" rotation="0" />
    <ExternalAgent type="Butterfly" material="" x="8.7294" y="-2.84" rotation="0" />
  </GameObjects>
</Level>
