<?xml version="1.0" encoding="utf-16"?>
<Level width="2">
  <Camera x="0" y="-1" minWidth="25" maxWidth="35" />
  <Score highScore="0" />
  <Birds>
    <Bird type="BirdRed"/>
  </Birds>
  <Slingshot x="-12.0" y="-2.5" />
  <GameObjects>
    <Pig type="BasicSmall" material="" x="-4.8309" y="-0.427" rotation="0.5998" />
    <Platform type="Platform" material="" x="-5.2882" y="-1.0161" rotation="0.0" scaleX="4.0152" scaleY="0.5" />
    <Platform type="Platform" material="" x="-3.8959" y="-0.0734" rotation="90.0" scaleX="3.4302" scaleY="0.4992" />
    <Platform type="Platform" material="" x="-4.9435" y="-0.9002" rotation="0.0" scaleX="3.2951" scaleY="0.7871" />
    <Platform type="Platform" material="" x="-6.1559" y="0.0459" rotation="0.0" scaleX="0.478" scaleY="2.995" />
    <Block type="RectTiny" material="wood" x="-3.3131" y="-3.39" rotation="0" />
    <Platform type="Platform" material="" x="-6.8692" y="-3.18" rotation="0" scaleX="1.0" scaleY="1.0" />
    <Block type="RectSmall" material="ice" x="4.5658" y="-3.39" rotation="0" />
  </GameObjects>
</Level>
